LICENSE
MANIFEST.in
README.md
setup.py
core/__init__.py
core/client.py
core/helpers.py
core/interface.py
hbtn_cli.egg-info/PKG-INFO
hbtn_cli.egg-info/SOURCES.txt
hbtn_cli.egg-info/dependency_links.txt
hbtn_cli.egg-info/entry_points.txt
hbtn_cli.egg-info/requires.txt
hbtn_cli.egg-info/top_level.txt