Metadata-Version: 2.1
Name: hbtn-cli
Version: 2.0.0
Summary: Automates Holberton School projects creation.
Home-page: https://github.com/maleksal/hbtn-cli
Author: Malek Salem
Author-email: 1419@holbertonschool.com
License: MIT License
Platform: UNKNOWN
Classifier: Programming Language :: Python :: 3
Classifier: License :: OSI Approved :: MIT License
Classifier: Operating System :: Microsoft :: Windows
Classifier: Operating System :: Unix
Requires-Python: >=3.5
License-File: LICENSE
